<PAMDataset>
  <Metadata>
    <MDI key="DataType">Generic</MDI>
  </Metadata>
  <PAMRasterBand band="1">
    <Histograms>
      <HistItem>
        <HistMin>0</HistMin>
        <HistMax>73.70175933837891</HistMax>
        <BucketCount>256</BucketCount>
        <IncludeOutOfRange>1</IncludeOutOfRange>
        <Approximate>0</Approximate>
        <HistCounts>137231|276213|288219|279565|247650|219630|199726|180300|163826|148888|137937|126827|117825|110043|103105|97937|93516|89189|85487|81703|78902|76486|72879|70774|68563|66660|64706|63209|61705|59998|58915|57367|56603|55439|54519|53206|52137|51128|50045|49156|48423|47084|46235|45133|44517|43592|42677|41709|40689|39568|38979|38398|37095|36507|35244|34929|33822|33114|32167|31487|30857|29934|29611|28582|28365|27143|26769|25733|25331|24415|24170|23290|22948|22527|21879|21439|21226|20583|19773|19610|19030|18707|18118|17550|17142|16787|16097|15943|15288|14781|14240|13959|13721|13114|12665|12265|11626|11430|10900|10569|10189|9680|9473|9167|8813|8455|8140|7863|7542|7298|6821|6642|6340|5899|5717|5644|5332|4957|4784|4519|4280|4178|3949|3726|3497|3310|3237|3071|2924|2824|2574|2459|2325|2207|2110|1961|1908|1894|1778|1655|1573|1510|1448|1402|1334|1268|1229|1133|1079|1013|997|925|910|901|799|798|776|745|702|608|642|606|570|534|501|484|425|447|442|398|391|330|323|321|304|310|286|259|277|233|217|210|205|196|172|177|149|137|151|121|129|123|124|107|115|93|102|92|96|81|57|79|71|68|54|55|57|63|64|47|45|41|48|33|40|34|23|29|22|26|14|27|28|24|13|16|21|22|18|15|5|11|10|11|16|12|13|11|10|5|11|7|10|1|7|4|6|7|6|4|4|3|3|2|0|1</HistCounts>
      </HistItem>
    </Histograms>
    <Metadata>
      <MDI key="RepresentationType">ATHEMATIC</MDI>
      <MDI key="STATISTICS_COVARIANCES">78.15025062771149</MDI>
      <MDI key="STATISTICS_EXCLUDEDVALUES"></MDI>
      <MDI key="STATISTICS_MAXIMUM">73.701759338379</MDI>
      <MDI key="STATISTICS_MEAN">8.7450698708489</MDI>
      <MDI key="STATISTICS_MINIMUM">0</MDI>
      <MDI key="STATISTICS_SKIPFACTORX">1</MDI>
      <MDI key="STATISTICS_SKIPFACTORY">1</MDI>
      <MDI key="STATISTICS_STDDEV">8.8402630406403</MDI>
    </Metadata>
  </PAMRasterBand>
</PAMDataset>
