<PAMDataset>
  <Metadata>
    <MDI key="DataType">Generic</MDI>
  </Metadata>
  <PAMRasterBand band="1">
    <Histograms>
      <HistItem>
        <HistMin>0</HistMin>
        <HistMax>52.01482009887695</HistMax>
        <BucketCount>256</BucketCount>
        <IncludeOutOfRange>1</IncludeOutOfRange>
        <Approximate>0</Approximate>
        <HistCounts>2462516|2042934|1025561|526644|347194|268583|225940|199488|177079|159634|146403|133083|122944|112775|104729|96291|89143|83142|77041|72041|67848|63272|59365|55251|52163|48866|46680|44011|41515|39383|36952|35150|33249|31663|30207|28747|27314|26063|25242|23875|23156|21942|21256|20251|19369|18636|18267|17652|16705|16480|15817|15048|14698|14206|13835|13434|12930|12466|12178|11717|11317|11168|10664|10454|9975|9834|9679|9310|9189|8762|8658|8392|8250|7967|7587|7553|7413|7281|6870|6834|6462|6481|6229|6151|6122|5982|5681|5752|5702|5427|5370|5224|5150|5018|4939|4984|4786|4787|4587|4405|4375|4292|4240|4125|3936|3866|3789|3669|3614|3447|3413|3304|3271|3141|3009|2996|2902|2784|2715|2739|2612|2544|2559|2372|2368|2306|2245|2148|2041|1929|1901|1818|1838|1732|1660|1616|1621|1561|1408|1459|1353|1297|1292|1210|1136|1108|1097|985|1014|987|959|894|844|852|807|789|775|710|771|669|772|643|605|634|632|594|528|510|489|494|445|421|413|354|316|314|300|286|255|226|204|224|179|156|164|154|134|134|123|101|112|84|90|94|90|68|76|87|81|64|62|57|57|51|40|43|34|35|31|18|26|24|23|15|18|25|14|24|15|12|2|8|17|9|5|4|8|6|8|8|8|5|3|2|2|3|2|3|2|3|1|2|1|1|2|3|0|0|1|3|0|0|0|1|0|1</HistCounts>
      </HistItem>
    </Histograms>
    <Metadata>
      <MDI key="RepresentationType">ATHEMATIC</MDI>
      <MDI key="STATISTICS_COVARIANCES">18.96415296933733</MDI>
      <MDI key="STATISTICS_EXCLUDEDVALUES"></MDI>
      <MDI key="STATISTICS_MAXIMUM">52.014820098877</MDI>
      <MDI key="STATISTICS_MEAN">2.2574994946937</MDI>
      <MDI key="STATISTICS_MINIMUM">0</MDI>
      <MDI key="STATISTICS_SKIPFACTORX">1</MDI>
      <MDI key="STATISTICS_SKIPFACTORY">1</MDI>
      <MDI key="STATISTICS_STDDEV">4.3547850658026</MDI>
    </Metadata>
  </PAMRasterBand>
</PAMDataset>
