{
  "build": "nompi_h4d922ce_1114",
  "build_number": 1114,
  "channel": "https://conda.anaconda.org/conda-forge/win-64",
  "constrains": [],
  "depends": [
    "vc >=14.1,<15.0a0",
    "vs2015_runtime >=14.16.27012",
    "zlib >=1.2.11,<1.3.0a0"
  ],
  "extracted_package_dir": "C:\\Users\\Lewis\\AppData\\Local\\ESRI\\conda\\pkgs\\hdf5-1.10.5-nompi_h4d922ce_1114",
  "features": "",
  "files": [
    "Library/COPYING",
    "Library/RELEASE.txt",
    "Library/USING_HDF5_CMake.txt",
    "Library/USING_HDF5_VS.txt",
    "Library/bin/gif2h5.exe",
    "Library/bin/h52gif.exe",
    "Library/bin/h5clear.exe",
    "Library/bin/h5copy-shared.exe",
    "Library/bin/h5copy.exe",
    "Library/bin/h5debug.exe",
    "Library/bin/h5diff-shared.exe",
    "Library/bin/h5diff.exe",
    "Library/bin/h5dump-shared.exe",
    "Library/bin/h5dump.exe",
    "Library/bin/h5format_convert.exe",
    "Library/bin/h5import.exe",
    "Library/bin/h5jam.exe",
    "Library/bin/h5ls-shared.exe",
    "Library/bin/h5ls.exe",
    "Library/bin/h5mkgrp.exe",
    "Library/bin/h5repack-shared.exe",
    "Library/bin/h5repack.exe",
    "Library/bin/h5repart.exe",
    "Library/bin/h5stat-shared.exe",
    "Library/bin/h5stat.exe",
    "Library/bin/h5unjam.exe",
    "Library/bin/h5watch.exe",
    "Library/bin/hdf5.dll",
    "Library/bin/hdf5_cpp.dll",
    "Library/bin/hdf5_hl.dll",
    "Library/bin/hdf5_hl_cpp.dll",
    "Library/bin/hdf5_tools.dll",
    "Library/cmake/hdf5/hdf5-config-version.cmake",
    "Library/cmake/hdf5/hdf5-config.cmake",
    "Library/cmake/hdf5/hdf5-targets-release.cmake",
    "Library/cmake/hdf5/hdf5-targets.cmake",
    "Library/include/H5ACpublic.h",
    "Library/include/H5AbstractDs.h",
    "Library/include/H5Alltypes.h",
    "Library/include/H5Apublic.h",
    "Library/include/H5ArrayType.h",
    "Library/include/H5AtomType.h",
    "Library/include/H5Attribute.h",
    "Library/include/H5Classes.h",
    "Library/include/H5CommonFG.h",
    "Library/include/H5CompType.h",
    "Library/include/H5Cpp.h",
    "Library/include/H5CppDoc.h",
    "Library/include/H5Cpublic.h",
    "Library/include/H5DOpublic.h",
    "Library/include/H5DSpublic.h",
    "Library/include/H5DaccProp.h",
    "Library/include/H5DataSet.h",
    "Library/include/H5DataSpace.h",
    "Library/include/H5DataType.h",
    "Library/include/H5DcreatProp.h",
    "Library/include/H5Dpublic.h",
    "Library/include/H5DxferProp.h",
    "Library/include/H5EnumType.h",
    "Library/include/H5Epubgen.h",
    "Library/include/H5Epublic.h",
    "Library/include/H5Exception.h",
    "Library/include/H5FDcore.h",
    "Library/include/H5FDdirect.h",
    "Library/include/H5FDfamily.h",
    "Library/include/H5FDlog.h",
    "Library/include/H5FDmpi.h",
    "Library/include/H5FDmpio.h",
    "Library/include/H5FDmulti.h",
    "Library/include/H5FDpublic.h",
    "Library/include/H5FDsec2.h",
    "Library/include/H5FDstdio.h",
    "Library/include/H5FDwindows.h",
    "Library/include/H5FaccProp.h",
    "Library/include/H5FcreatProp.h",
    "Library/include/H5File.h",
    "Library/include/H5FloatType.h",
    "Library/include/H5Fpublic.h",
    "Library/include/H5Gpublic.h",
    "Library/include/H5Group.h",
    "Library/include/H5IMpublic.h",
    "Library/include/H5IdComponent.h",
    "Library/include/H5Include.h",
    "Library/include/H5IntType.h",
    "Library/include/H5Ipublic.h",
    "Library/include/H5LDpublic.h",
    "Library/include/H5LTpublic.h",
    "Library/include/H5LaccProp.h",
    "Library/include/H5LcreatProp.h",
    "Library/include/H5Library.h",
    "Library/include/H5Location.h",
    "Library/include/H5Lpublic.h",
    "Library/include/H5MMpublic.h",
    "Library/include/H5Object.h",
    "Library/include/H5OcreatProp.h",
    "Library/include/H5Opublic.h",
    "Library/include/H5PLextern.h",
    "Library/include/H5PLpublic.h",
    "Library/include/H5PTpublic.h",
    "Library/include/H5PacketTable.h",
    "Library/include/H5Ppublic.h",
    "Library/include/H5PredType.h",
    "Library/include/H5PropList.h",
    "Library/include/H5Rpublic.h",
    "Library/include/H5Spublic.h",
    "Library/include/H5StrType.h",
    "Library/include/H5TBpublic.h",
    "Library/include/H5Tpublic.h",
    "Library/include/H5VarLenType.h",
    "Library/include/H5Zpublic.h",
    "Library/include/H5api_adpt.h",
    "Library/include/H5overflow.h",
    "Library/include/H5pubconf.h",
    "Library/include/H5public.h",
    "Library/include/H5version.h",
    "Library/include/hdf5.h",
    "Library/include/hdf5_hl.h",
    "Library/lib/hdf5.lib",
    "Library/lib/hdf5_cpp.lib",
    "Library/lib/hdf5_hl.lib",
    "Library/lib/hdf5_hl_cpp.lib",
    "Library/lib/hdf5_tools.lib",
    "Library/lib/libhdf5.lib",
    "Library/lib/libhdf5.settings",
    "Library/lib/libhdf5_cpp.lib",
    "Library/lib/libhdf5_hl.lib",
    "Library/lib/libhdf5_hl_cpp.lib",
    "Library/lib/libhdf5_tools.lib",
    "Library/lib/pkgconfig/hdf5-1.10.5.pc",
    "Library/lib/pkgconfig/hdf5_cpp-1.10.5.pc",
    "Library/lib/pkgconfig/hdf5_hl-1.10.5.pc",
    "Library/lib/pkgconfig/hdf5_hl_cpp-1.10.5.pc",
    ".nonadmin"
  ],
  "fn": "hdf5-1.10.5-nompi_h4d922ce_1114.tar.bz2",
  "license": "LicenseRef-HDF5",
  "license_family": "BSD",
  "link": {
    "source": "C:\\Users\\Lewis\\AppData\\Local\\ESRI\\conda\\pkgs\\hdf5-1.10.5-nompi_h4d922ce_1114",
    "type": 1
  },
  "md5": "6c6187c8a71bb0625f8dd00728e38173",
  "name": "hdf5",
  "package_tarball_full_path": "C:\\Users\\Lewis\\AppData\\Local\\ESRI\\conda\\pkgs\\hdf5-1.10.5-nompi_h4d922ce_1114.tar.bz2",
  "paths_data": {
    "paths": [
      {
        "_path": "Library/COPYING",
        "path_type": "hardlink",
        "sha256": "71050851a007288f4a79fe4ca3106ff83a35124ddc6c7f0f29018a295180b940",
        "sha256_in_prefix": "71050851a007288f4a79fe4ca3106ff83a35124ddc6c7f0f29018a295180b940",
        "size_in_bytes": 558
      },
      {
        "_path": "Library/RELEASE.txt",
        "path_type": "hardlink",
        "sha256": "288099fe37cdff674177ce3c130a28bdcafeab0ef81a2d7588adf7df5f3de1f1",
        "sha256_in_prefix": "288099fe37cdff674177ce3c130a28bdcafeab0ef81a2d7588adf7df5f3de1f1",
        "size_in_bytes": 27927
      },
      {
        "_path": "Library/USING_HDF5_CMake.txt",
        "path_type": "hardlink",
        "sha256": "fdb5fe21b6a1582043d8ff999794b79430964655cc7f2531ecf56c5e38e73d59",
        "sha256_in_prefix": "fdb5fe21b6a1582043d8ff999794b79430964655cc7f2531ecf56c5e38e73d59",
        "size_in_bytes": 9447
      },
      {
        "_path": "Library/USING_HDF5_VS.txt",
        "path_type": "hardlink",
        "sha256": "d1ebd700beaaa22512bc8b8448ee74847f920dcc8b7280d91b8244f90d02f195",
        "sha256_in_prefix": "d1ebd700beaaa22512bc8b8448ee74847f920dcc8b7280d91b8244f90d02f195",
        "size_in_bytes": 3853
      },
      {
        "_path": "Library/bin/gif2h5.exe",
        "path_type": "hardlink",
        "sha256": "a05c0ae5d90a791b56ad7046dd59283294e673d2efba0c4e2319ef7ca5e941fa",
        "sha256_in_prefix": "a05c0ae5d90a791b56ad7046dd59283294e673d2efba0c4e2319ef7ca5e941fa",
        "size_in_bytes": 2398720
      },
      {
        "_path": "Library/bin/h52gif.exe",
        "path_type": "hardlink",
        "sha256": "b5aacce7e7eff96f4b6285cf50958a97fc02c869998bb083726705b2304930a2",
        "sha256_in_prefix": "b5aacce7e7eff96f4b6285cf50958a97fc02c869998bb083726705b2304930a2",
        "size_in_bytes": 2366976
      },
      {
        "_path": "Library/bin/h5clear.exe",
        "path_type": "hardlink",
        "sha256": "fb3a0e4bd79c6a4092d48b7415f82450d11b5b8f7663c94e2ad7d59c26986391",
        "sha256_in_prefix": "fb3a0e4bd79c6a4092d48b7415f82450d11b5b8f7663c94e2ad7d59c26986391",
        "size_in_bytes": 2325504
      },
      {
        "_path": "Library/bin/h5copy-shared.exe",
        "path_type": "hardlink",
        "sha256": "1adb367519142164315598ec366055ebab358cbfe1f3fa4495446b7820f89659",
        "sha256_in_prefix": "1adb367519142164315598ec366055ebab358cbfe1f3fa4495446b7820f89659",
        "size_in_bytes": 18944
      },
      {
        "_path": "Library/bin/h5copy.exe",
        "path_type": "hardlink",
        "sha256": "960d7a34719081218ce7acd80cfda6217f4296eec805131d987105f8913e38ca",
        "sha256_in_prefix": "960d7a34719081218ce7acd80cfda6217f4296eec805131d987105f8913e38ca",
        "size_in_bytes": 2348032
      },
      {
        "_path": "Library/bin/h5debug.exe",
        "path_type": "hardlink",
        "sha256": "83880767b488fbc922ef9c79305ca2009ef46f515c637756ecb07316fabd3b2d",
        "sha256_in_prefix": "83880767b488fbc922ef9c79305ca2009ef46f515c637756ecb07316fabd3b2d",
        "size_in_bytes": 2332672
      },
      {
        "_path": "Library/bin/h5diff-shared.exe",
        "path_type": "hardlink",
        "sha256": "3a055c89fff1031473ac0cfd62e0fc94e1f5afa52895f3b4b239d7317cef524f",
        "sha256_in_prefix": "3a055c89fff1031473ac0cfd62e0fc94e1f5afa52895f3b4b239d7317cef524f",
        "size_in_bytes": 26112
      },
      {
        "_path": "Library/bin/h5diff.exe",
        "path_type": "hardlink",
        "sha256": "608c03205de79564be85a9cddb9790f20904041b4aa32e854dd27b13013fbb38",
        "sha256_in_prefix": "608c03205de79564be85a9cddb9790f20904041b4aa32e854dd27b13013fbb38",
        "size_in_bytes": 2512384
      },
      {
        "_path": "Library/bin/h5dump-shared.exe",
        "path_type": "hardlink",
        "sha256": "69c2e0bf5d47603981f1ad5915b4e85bc224397df5d2fb10e7b286892f45c8a7",
        "sha256_in_prefix": "69c2e0bf5d47603981f1ad5915b4e85bc224397df5d2fb10e7b286892f45c8a7",
        "size_in_bytes": 112128
      },
      {
        "_path": "Library/bin/h5dump.exe",
        "path_type": "hardlink",
        "sha256": "d023c8261455af578cf650dc5f36e49e0e8bdc94186f7f46f7be2e50317d4002",
        "sha256_in_prefix": "d023c8261455af578cf650dc5f36e49e0e8bdc94186f7f46f7be2e50317d4002",
        "size_in_bytes": 2635776
      },
      {
        "_path": "Library/bin/h5format_convert.exe",
        "path_type": "hardlink",
        "sha256": "d69dde3396f439aa8b9db7536a62d53dec8cb887dd951c59f3a745bc4ac48052",
        "sha256_in_prefix": "d69dde3396f439aa8b9db7536a62d53dec8cb887dd951c59f3a745bc4ac48052",
        "size_in_bytes": 2343424
      },
      {
        "_path": "Library/bin/h5import.exe",
        "path_type": "hardlink",
        "sha256": "2d8d7ca030ee6886434539286d622267438a754ae2856c468143332cfe6e6711",
        "sha256_in_prefix": "2d8d7ca030ee6886434539286d622267438a754ae2856c468143332cfe6e6711",
        "size_in_bytes": 2391040
      },
      {
        "_path": "Library/bin/h5jam.exe",
        "path_type": "hardlink",
        "sha256": "209caf8e761f3839079717897c4c1863b2d10aebf7df531dbd6b25b6e523fefe",
        "sha256_in_prefix": "209caf8e761f3839079717897c4c1863b2d10aebf7df531dbd6b25b6e523fefe",
        "size_in_bytes": 2320384
      },
      {
        "_path": "Library/bin/h5ls-shared.exe",
        "path_type": "hardlink",
        "sha256": "f34223268867b8e4798eb6dfdeca493cf131d3be759a5cb4eb8ad0d22e823f49",
        "sha256_in_prefix": "f34223268867b8e4798eb6dfdeca493cf131d3be759a5cb4eb8ad0d22e823f49",
        "size_in_bytes": 52736
      },
      {
        "_path": "Library/bin/h5ls.exe",
        "path_type": "hardlink",
        "sha256": "ea37f82593b57772fbc041b7aae5793861d746e3e124b3cf350b19e13f619ab8",
        "sha256_in_prefix": "ea37f82593b57772fbc041b7aae5793861d746e3e124b3cf350b19e13f619ab8",
        "size_in_bytes": 2511872
      },
      {
        "_path": "Library/bin/h5mkgrp.exe",
        "path_type": "hardlink",
        "sha256": "fefacd3964cde279e32d2f218b437458d4553341a240c0a4b86e0212d00b73c4",
        "sha256_in_prefix": "fefacd3964cde279e32d2f218b437458d4553341a240c0a4b86e0212d00b73c4",
        "size_in_bytes": 2324480
      },
      {
        "_path": "Library/bin/h5repack-shared.exe",
        "path_type": "hardlink",
        "sha256": "3abc5bd0b49be8b3e8b608ebd86699a2a6a7755e4f81ef848372663773297381",
        "sha256_in_prefix": "3abc5bd0b49be8b3e8b608ebd86699a2a6a7755e4f81ef848372663773297381",
        "size_in_bytes": 87040
      },
      {
        "_path": "Library/bin/h5repack.exe",
        "path_type": "hardlink",
        "sha256": "1988c27fea4f63635ebf954b6c8c37f551d8aa867964a666d70387f521a68c54",
        "sha256_in_prefix": "1988c27fea4f63635ebf954b6c8c37f551d8aa867964a666d70387f521a68c54",
        "size_in_bytes": 2530304
      },
      {
        "_path": "Library/bin/h5repart.exe",
        "path_type": "hardlink",
        "sha256": "63fdaa423b02b7bfe79d98cc119b5322fc0bc6e9c413d8cb0e37a2a0994df70b",
        "sha256_in_prefix": "63fdaa423b02b7bfe79d98cc119b5322fc0bc6e9c413d8cb0e37a2a0994df70b",
        "size_in_bytes": 2271232
      },
      {
        "_path": "Library/bin/h5stat-shared.exe",
        "path_type": "hardlink",
        "sha256": "ecfb2466b8e036e77f0e6ccdde8e9d41827d99d436df6914f488fc6803b8c424",
        "sha256_in_prefix": "ecfb2466b8e036e77f0e6ccdde8e9d41827d99d436df6914f488fc6803b8c424",
        "size_in_bytes": 33792
      },
      {
        "_path": "Library/bin/h5stat.exe",
        "path_type": "hardlink",
        "sha256": "3fc51cb0283c4b91e0b703e5581b0d0432a7891c51c30773b766073edadb3f1b",
        "sha256_in_prefix": "3fc51cb0283c4b91e0b703e5581b0d0432a7891c51c30773b766073edadb3f1b",
        "size_in_bytes": 2371584
      },
      {
        "_path": "Library/bin/h5unjam.exe",
        "path_type": "hardlink",
        "sha256": "9a60875ddc47c7349ec50e59bdc56863d72bb90071502c2df443a572f9658b78",
        "sha256_in_prefix": "9a60875ddc47c7349ec50e59bdc56863d72bb90071502c2df443a572f9658b78",
        "size_in_bytes": 2319360
      },
      {
        "_path": "Library/bin/h5watch.exe",
        "path_type": "hardlink",
        "sha256": "ef5376c822aab9dff320f55788a86f3e2682c6db8c6896795af7f98c7037fc6d",
        "sha256_in_prefix": "ef5376c822aab9dff320f55788a86f3e2682c6db8c6896795af7f98c7037fc6d",
        "size_in_bytes": 2460672
      },
      {
        "_path": "Library/bin/hdf5.dll",
        "path_type": "hardlink",
        "sha256": "7ff714833b9a7753d9b6f42413d9bd0ed88304a06d516822e65dc6b45597f227",
        "sha256_in_prefix": "7ff714833b9a7753d9b6f42413d9bd0ed88304a06d516822e65dc6b45597f227",
        "size_in_bytes": 3150336
      },
      {
        "_path": "Library/bin/hdf5_cpp.dll",
        "path_type": "hardlink",
        "sha256": "eb806752c84a20cd9d770220a10297b21a4502dcf8656bf6f9cbf77a9e9f7809",
        "sha256_in_prefix": "eb806752c84a20cd9d770220a10297b21a4502dcf8656bf6f9cbf77a9e9f7809",
        "size_in_bytes": 340992
      },
      {
        "_path": "Library/bin/hdf5_hl.dll",
        "path_type": "hardlink",
        "sha256": "7b015823af32cb50b177c41b98912e923b857c70e53d1998fe7c609daa82d051",
        "sha256_in_prefix": "7b015823af32cb50b177c41b98912e923b857c70e53d1998fe7c609daa82d051",
        "size_in_bytes": 116224
      },
      {
        "_path": "Library/bin/hdf5_hl_cpp.dll",
        "path_type": "hardlink",
        "sha256": "bc5944b9cc63f4fb00a37469ba2b89802f3577d80f22837593b8d2f6ed3b0066",
        "sha256_in_prefix": "bc5944b9cc63f4fb00a37469ba2b89802f3577d80f22837593b8d2f6ed3b0066",
        "size_in_bytes": 14848
      },
      {
        "_path": "Library/bin/hdf5_tools.dll",
        "path_type": "hardlink",
        "sha256": "f86d1e9e97ad48fc0034307661de97ef30a46d4304af19e6a81a4601658a9453",
        "sha256_in_prefix": "f86d1e9e97ad48fc0034307661de97ef30a46d4304af19e6a81a4601658a9453",
        "size_in_bytes": 197120
      },
      {
        "_path": "Library/cmake/hdf5/hdf5-config-version.cmake",
        "path_type": "hardlink",
        "sha256": "7e7ffe7b7a9e94cc2db27b1e018cf13648586ab14814244947879d54915880a4",
        "sha256_in_prefix": "7e7ffe7b7a9e94cc2db27b1e018cf13648586ab14814244947879d54915880a4",
        "size_in_bytes": 2239
      },
      {
        "_path": "Library/cmake/hdf5/hdf5-config.cmake",
        "path_type": "hardlink",
        "sha256": "503e1b870f63c4b563b1ec3f84cb3e1d5efe0a3a44b41e8f11ae29526ec3b179",
        "sha256_in_prefix": "503e1b870f63c4b563b1ec3f84cb3e1d5efe0a3a44b41e8f11ae29526ec3b179",
        "size_in_bytes": 9562
      },
      {
        "_path": "Library/cmake/hdf5/hdf5-targets-release.cmake",
        "path_type": "hardlink",
        "sha256": "1f95b67aa3977c6ee6f029ca2d80f15ece0f512e86f15cb1f091b5a75b94c5e7",
        "sha256_in_prefix": "1f95b67aa3977c6ee6f029ca2d80f15ece0f512e86f15cb1f091b5a75b94c5e7",
        "size_in_bytes": 15281
      },
      {
        "_path": "Library/cmake/hdf5/hdf5-targets.cmake",
        "file_mode": "text",
        "path_type": "hardlink",
        "prefix_placeholder": "D:/bld/hdf5_split_1610146385506/_h_env",
        "sha256": "d86e2002af0853a80efc55ed83543a1f2bc2fdacd3507359092f422b913f4578",
        "sha256_in_prefix": "d4e73a39a695674e820711cf123a9774eb9f7548d7e2c0248520f37e3af6617d",
        "size_in_bytes": 9942
      },
      {
        "_path": "Library/include/H5ACpublic.h",
        "path_type": "hardlink",
        "sha256": "a0f6bab4325719bd381b08487af76d616b467aad94ba803aa31f2793de266bcf",
        "sha256_in_prefix": "a0f6bab4325719bd381b08487af76d616b467aad94ba803aa31f2793de266bcf",
        "size_in_bytes": 25488
      },
      {
        "_path": "Library/include/H5AbstractDs.h",
        "path_type": "hardlink",
        "sha256": "01ea9f2eac372ce265d012b9430d35aaff5b3aa3e5c8d1ea4af1c17933ef33ef",
        "sha256_in_prefix": "01ea9f2eac372ce265d012b9430d35aaff5b3aa3e5c8d1ea4af1c17933ef33ef",
        "size_in_bytes": 3157
      },
      {
        "_path": "Library/include/H5Alltypes.h",
        "path_type": "hardlink",
        "sha256": "58d65399d0d5075e2ed9231f5cc49fbbc5f1dad243d4e2621c8a088f9911b53a",
        "sha256_in_prefix": "58d65399d0d5075e2ed9231f5cc49fbbc5f1dad243d4e2621c8a088f9911b53a",
        "size_in_bytes": 1379
      },
      {
        "_path": "Library/include/H5Apublic.h",
        "path_type": "hardlink",
        "sha256": "34c64250711904ef6eec64cd91518eda6390efb6e028bcf8c19446e373da784b",
        "sha256_in_prefix": "34c64250711904ef6eec64cd91518eda6390efb6e028bcf8c19446e373da784b",
        "size_in_bytes": 5471
      },
      {
        "_path": "Library/include/H5ArrayType.h",
        "path_type": "hardlink",
        "sha256": "788cfa2fe292253b5fe6f9cd562dff9d23a7d873e6c6688665dffaeb58b2b814",
        "sha256_in_prefix": "788cfa2fe292253b5fe6f9cd562dff9d23a7d873e6c6688665dffaeb58b2b814",
        "size_in_bytes": 2807
      },
      {
        "_path": "Library/include/H5AtomType.h",
        "path_type": "hardlink",
        "sha256": "51f38fbd8b7e9ae4082a077dc467789b461a0a1f1f434a47d149fd3be29257cb",
        "sha256_in_prefix": "51f38fbd8b7e9ae4082a077dc467789b461a0a1f1f434a47d149fd3be29257cb",
        "size_in_bytes": 3155
      },
      {
        "_path": "Library/include/H5Attribute.h",
        "path_type": "hardlink",
        "sha256": "f413e33b1cd658429d5a1f777a7aa7eb5fc8c9d02f3c1d0c38b38e78ec9aeabc",
        "sha256_in_prefix": "f413e33b1cd658429d5a1f777a7aa7eb5fc8c9d02f3c1d0c38b38e78ec9aeabc",
        "size_in_bytes": 4281
      },
      {
        "_path": "Library/include/H5Classes.h",
        "path_type": "hardlink",
        "sha256": "c6d906e7e431c6d7c09f2977c395282790ebb2605f5fbc8001afe4578c5646a0",
        "sha256_in_prefix": "c6d906e7e431c6d7c09f2977c395282790ebb2605f5fbc8001afe4578c5646a0",
        "size_in_bytes": 1770
      },
      {
        "_path": "Library/include/H5CommonFG.h",
        "path_type": "hardlink",
        "sha256": "488ebb25ffbf1c2364e0baa01fabe4b8623e94e25641e3e36344efa77adff219",
        "sha256_in_prefix": "488ebb25ffbf1c2364e0baa01fabe4b8623e94e25641e3e36344efa77adff219",
        "size_in_bytes": 3761
      },
      {
        "_path": "Library/include/H5CompType.h",
        "path_type": "hardlink",
        "sha256": "cd99a417e273f7c504cb5dd431a43c041e8a0eba4a14db19bf4a6b50529c8b7f",
        "sha256_in_prefix": "cd99a417e273f7c504cb5dd431a43c041e8a0eba4a14db19bf4a6b50529c8b7f",
        "size_in_bytes": 5099
      },
      {
        "_path": "Library/include/H5Cpp.h",
        "path_type": "hardlink",
        "sha256": "dba77add4fe1f1fad08b1df46d92bb8bd6262503ecce924562b299b6f90268b8",
        "sha256_in_prefix": "dba77add4fe1f1fad08b1df46d92bb8bd6262503ecce924562b299b6f90268b8",
        "size_in_bytes": 2089
      },
      {
        "_path": "Library/include/H5CppDoc.h",
        "path_type": "hardlink",
        "sha256": "68ccc8b30d2645d33be5728ed72c8452fc88cf2a9bc35ad4e66093a9479f99b0",
        "sha256_in_prefix": "68ccc8b30d2645d33be5728ed72c8452fc88cf2a9bc35ad4e66093a9479f99b0",
        "size_in_bytes": 3638
      },
      {
        "_path": "Library/include/H5Cpublic.h",
        "path_type": "hardlink",
        "sha256": "bde6b5f7c49d0cff9f6819b018d1d24309d2a683007ffa02ae70651e3543f1df",
        "sha256_in_prefix": "bde6b5f7c49d0cff9f6819b018d1d24309d2a683007ffa02ae70651e3543f1df",
        "size_in_bytes": 1760
      },
      {
        "_path": "Library/include/H5DOpublic.h",
        "path_type": "hardlink",
        "sha256": "908762440780c05c67ad6b2ec5feff03da326c50fd9447c52720e79915eb29eb",
        "sha256_in_prefix": "908762440780c05c67ad6b2ec5feff03da326c50fd9447c52720e79915eb29eb",
        "size_in_bytes": 1931
      },
      {
        "_path": "Library/include/H5DSpublic.h",
        "path_type": "hardlink",
        "sha256": "20c92e88c28d38ab1512e4f25e86c821446ca7a7e6201ddd830a217d280ac265",
        "sha256_in_prefix": "20c92e88c28d38ab1512e4f25e86c821446ca7a7e6201ddd830a217d280ac265",
        "size_in_bytes": 2590
      },
      {
        "_path": "Library/include/H5DaccProp.h",
        "path_type": "hardlink",
        "sha256": "ece98c63394f939a662dfb82c2ba07033a0bfdeae483c32fd50b98b4987c8826",
        "sha256_in_prefix": "ece98c63394f939a662dfb82c2ba07033a0bfdeae483c32fd50b98b4987c8826",
        "size_in_bytes": 2779
      },
      {
        "_path": "Library/include/H5DataSet.h",
        "path_type": "hardlink",
        "sha256": "2384f8bb41bd7e03efc116bd54abfd68438307c311d8834d25d67171f755b9e8",
        "sha256_in_prefix": "2384f8bb41bd7e03efc116bd54abfd68438307c311d8834d25d67171f755b9e8",
        "size_in_bytes": 7086
      },
      {
        "_path": "Library/include/H5DataSpace.h",
        "path_type": "hardlink",
        "sha256": "c911c687ecdf82048d658d297c0a4200caffdfb29697dc1ae07769b7ad4a0004",
        "sha256_in_prefix": "c911c687ecdf82048d658d297c0a4200caffdfb29697dc1ae07769b7ad4a0004",
        "size_in_bytes": 5757
      },
      {
        "_path": "Library/include/H5DataType.h",
        "path_type": "hardlink",
        "sha256": "978f03e1f286cd4ee68760f251870e2a259611e38f53c97f1808ef913aac1a20",
        "sha256_in_prefix": "978f03e1f286cd4ee68760f251870e2a259611e38f53c97f1808ef913aac1a20",
        "size_in_bytes": 7333
      },
      {
        "_path": "Library/include/H5DcreatProp.h",
        "path_type": "hardlink",
        "sha256": "a5b7822f4f6473566797c925a4b3efdaaa8180dd88f4349105c54f5db2460491",
        "sha256_in_prefix": "a5b7822f4f6473566797c925a4b3efdaaa8180dd88f4349105c54f5db2460491",
        "size_in_bytes": 6426
      },
      {
        "_path": "Library/include/H5Dpublic.h",
        "path_type": "hardlink",
        "sha256": "5d15d2fa7c8cc946927c428878e7a758fc66c8aca52398c84bf4bd7e3bdcfe8d",
        "sha256_in_prefix": "5d15d2fa7c8cc946927c428878e7a758fc66c8aca52398c84bf4bd7e3bdcfe8d",
        "size_in_bytes": 9022
      },
      {
        "_path": "Library/include/H5DxferProp.h",
        "path_type": "hardlink",
        "sha256": "405cc9111ece74b6b465e906878acc6175aa49d66eba71b6ba6c5418711c27cb",
        "sha256_in_prefix": "405cc9111ece74b6b465e906878acc6175aa49d66eba71b6ba6c5418711c27cb",
        "size_in_bytes": 5497
      },
      {
        "_path": "Library/include/H5EnumType.h",
        "path_type": "hardlink",
        "sha256": "8f0925e94b9211b253b84374ecd144d5e2c7b95d01b3b601bae6618ff4626779",
        "sha256_in_prefix": "8f0925e94b9211b253b84374ecd144d5e2c7b95d01b3b601bae6618ff4626779",
        "size_in_bytes": 3566
      },
      {
        "_path": "Library/include/H5Epubgen.h",
        "path_type": "hardlink",
        "sha256": "8384871f873f7edee02e3c4187118658b750cfb43e40fdc406565cbd9d7d2546",
        "sha256_in_prefix": "8384871f873f7edee02e3c4187118658b750cfb43e40fdc406565cbd9d7d2546",
        "size_in_bytes": 21996
      },
      {
        "_path": "Library/include/H5Epublic.h",
        "path_type": "hardlink",
        "sha256": "50d365b6496ff2bf168fd495e8c0ef305afbb4c03a29d93569008c63957ee473",
        "sha256_in_prefix": "50d365b6496ff2bf168fd495e8c0ef305afbb4c03a29d93569008c63957ee473",
        "size_in_bytes": 9023
      },
      {
        "_path": "Library/include/H5Exception.h",
        "path_type": "hardlink",
        "sha256": "867ded00af964593609dc46c654e5b42637c7255e678defbe9e263b6850d0ba3",
        "sha256_in_prefix": "867ded00af964593609dc46c654e5b42637c7255e678defbe9e263b6850d0ba3",
        "size_in_bytes": 6857
      },
      {
        "_path": "Library/include/H5FDcore.h",
        "path_type": "hardlink",
        "sha256": "cfd1dcd78e1c4dbd76eb3b04935c78be9e5e12458ce3a9b51ade259c18706ef7",
        "sha256_in_prefix": "cfd1dcd78e1c4dbd76eb3b04935c78be9e5e12458ce3a9b51ade259c18706ef7",
        "size_in_bytes": 1490
      },
      {
        "_path": "Library/include/H5FDdirect.h",
        "path_type": "hardlink",
        "sha256": "330dff30124a20bc3657a6077e254814f739d5ed067d92f1fef73554adbf93d1",
        "sha256_in_prefix": "330dff30124a20bc3657a6077e254814f739d5ed067d92f1fef73554adbf93d1",
        "size_in_bytes": 1955
      },
      {
        "_path": "Library/include/H5FDfamily.h",
        "path_type": "hardlink",
        "sha256": "69cb16c68d0b346dcbba807f5759f2cbfea95de984eccad6e033ca970b7cdeb3",
        "sha256_in_prefix": "69cb16c68d0b346dcbba807f5759f2cbfea95de984eccad6e033ca970b7cdeb3",
        "size_in_bytes": 1506
      },
      {
        "_path": "Library/include/H5FDlog.h",
        "path_type": "hardlink",
        "sha256": "d914aac7a027612e763a03c5fd54861d4c4760ba72a458065eb427b6ef510fa9",
        "sha256_in_prefix": "d914aac7a027612e763a03c5fd54861d4c4760ba72a458065eb427b6ef510fa9",
        "size_in_bytes": 3322
      },
      {
        "_path": "Library/include/H5FDmpi.h",
        "path_type": "hardlink",
        "sha256": "f04055d8d21140bb3531d6434093e3e352af2c534353bf56347c71223cb631cd",
        "sha256_in_prefix": "f04055d8d21140bb3531d6434093e3e352af2c534353bf56347c71223cb631cd",
        "size_in_bytes": 2573
      },
      {
        "_path": "Library/include/H5FDmpio.h",
        "path_type": "hardlink",
        "sha256": "29fb48ce4a6fc99cebe8967fcdc7d0be2f55606ecd4fa5beebcf12cef27f7319",
        "sha256_in_prefix": "29fb48ce4a6fc99cebe8967fcdc7d0be2f55606ecd4fa5beebcf12cef27f7319",
        "size_in_bytes": 2440
      },
      {
        "_path": "Library/include/H5FDmulti.h",
        "path_type": "hardlink",
        "sha256": "8e26aed1cbad3c46a618791e9b84e8318525a8e42f4c7bea301b5df50ac37bb2",
        "sha256_in_prefix": "8e26aed1cbad3c46a618791e9b84e8318525a8e42f4c7bea301b5df50ac37bb2",
        "size_in_bytes": 1800
      },
      {
        "_path": "Library/include/H5FDpublic.h",
        "path_type": "hardlink",
        "sha256": "3877766550052210d27d75773f38d04e08728ed3b925eb156ea374cae12da801",
        "sha256_in_prefix": "3877766550052210d27d75773f38d04e08728ed3b925eb156ea374cae12da801",
        "size_in_bytes": 17115
      },
      {
        "_path": "Library/include/H5FDsec2.h",
        "path_type": "hardlink",
        "sha256": "82781f0dad0e80d9ad04cfa96b3c0a059242ad19fd2445d5caeacdcb64150503",
        "sha256_in_prefix": "82781f0dad0e80d9ad04cfa96b3c0a059242ad19fd2445d5caeacdcb64150503",
        "size_in_bytes": 1339
      },
      {
        "_path": "Library/include/H5FDstdio.h",
        "path_type": "hardlink",
        "sha256": "f23f540a76d5ee52175a500792075d6d91daa019ae6a54f33a10223f39a09d1b",
        "sha256_in_prefix": "f23f540a76d5ee52175a500792075d6d91daa019ae6a54f33a10223f39a09d1b",
        "size_in_bytes": 1368
      },
      {
        "_path": "Library/include/H5FDwindows.h",
        "path_type": "hardlink",
        "sha256": "61bb43fd5e04ce8c485764ae7510d7f7a1dd95f9077742f0c923bb0a100bff7a",
        "sha256_in_prefix": "61bb43fd5e04ce8c485764ae7510d7f7a1dd95f9077742f0c923bb0a100bff7a",
        "size_in_bytes": 1414
      },
      {
        "_path": "Library/include/H5FaccProp.h",
        "path_type": "hardlink",
        "sha256": "f650b7347c622e29cb1abf90632c355cd1e16783a7ab18d8542c21106936107c",
        "sha256_in_prefix": "f650b7347c622e29cb1abf90632c355cd1e16783a7ab18d8542c21106936107c",
        "size_in_bytes": 6951
      },
      {
        "_path": "Library/include/H5FcreatProp.h",
        "path_type": "hardlink",
        "sha256": "a8c18b84ae2764d57825e61f0ddcbaabd96393130d6dd14da6ab62095334c8ca",
        "sha256_in_prefix": "a8c18b84ae2764d57825e61f0ddcbaabd96393130d6dd14da6ab62095334c8ca",
        "size_in_bytes": 4579
      },
      {
        "_path": "Library/include/H5File.h",
        "path_type": "hardlink",
        "sha256": "9a039cb535313d2a94f77d867d241bbc60d8b00f2c20b9fd48146cef692300a4",
        "sha256_in_prefix": "9a039cb535313d2a94f77d867d241bbc60d8b00f2c20b9fd48146cef692300a4",
        "size_in_bytes": 5060
      },
      {
        "_path": "Library/include/H5FloatType.h",
        "path_type": "hardlink",
        "sha256": "7133de087b7bcc0fcd26d234027b0ce2e1539c4d04dd8567982fc7ea220bc0f1",
        "sha256_in_prefix": "7133de087b7bcc0fcd26d234027b0ce2e1539c4d04dd8567982fc7ea220bc0f1",
        "size_in_bytes": 3493
      },
      {
        "_path": "Library/include/H5Fpublic.h",
        "path_type": "hardlink",
        "sha256": "4e0af967644fa10cacc75222a105f6bd5f60d1d8d5059464970811aa8d7cebb3",
        "sha256_in_prefix": "4e0af967644fa10cacc75222a105f6bd5f60d1d8d5059464970811aa8d7cebb3",
        "size_in_bytes": 14688
      },
      {
        "_path": "Library/include/H5Gpublic.h",
        "path_type": "hardlink",
        "sha256": "129861347ceaf1950e81210781eafa78fefe4518eb645d20b59ae2787860130d",
        "sha256_in_prefix": "129861347ceaf1950e81210781eafa78fefe4518eb645d20b59ae2787860130d",
        "size_in_bytes": 7233
      },
      {
        "_path": "Library/include/H5Group.h",
        "path_type": "hardlink",
        "sha256": "2db183f4af19984bd1a6adc5f2b88dec1776a6f318f560835dffac3576063be9",
        "sha256_in_prefix": "2db183f4af19984bd1a6adc5f2b88dec1776a6f318f560835dffac3576063be9",
        "size_in_bytes": 3119
      },
      {
        "_path": "Library/include/H5IMpublic.h",
        "path_type": "hardlink",
        "sha256": "f334a633f2bc1c6e1e4c293632145da030dfd18a8e834ab2c8edcc1bd41153a3",
        "sha256_in_prefix": "f334a633f2bc1c6e1e4c293632145da030dfd18a8e834ab2c8edcc1bd41153a3",
        "size_in_bytes": 3274
      },
      {
        "_path": "Library/include/H5IdComponent.h",
        "path_type": "hardlink",
        "sha256": "d0e31fe46cc18569a7f9b16dbeae40b24fd498fc8e6c92979faa319ac850527d",
        "sha256_in_prefix": "d0e31fe46cc18569a7f9b16dbeae40b24fd498fc8e6c92979faa319ac850527d",
        "size_in_bytes": 4002
      },
      {
        "_path": "Library/include/H5Include.h",
        "path_type": "hardlink",
        "sha256": "cb9ad389cd1a819b0ddabdc5213849bff758518a5eadb52693934793b4a26fed",
        "sha256_in_prefix": "cb9ad389cd1a819b0ddabdc5213849bff758518a5eadb52693934793b4a26fed",
        "size_in_bytes": 1622
      },
      {
        "_path": "Library/include/H5IntType.h",
        "path_type": "hardlink",
        "sha256": "0e28525afd0662772aeb91b52971ef22e1eadad64e4baa064f2cb9bd57acab82",
        "sha256_in_prefix": "0e28525afd0662772aeb91b52971ef22e1eadad64e4baa064f2cb9bd57acab82",
        "size_in_bytes": 2573
      },
      {
        "_path": "Library/include/H5Ipublic.h",
        "path_type": "hardlink",
        "sha256": "444e13f8d25bc0e1b513720f65e17216f6e20da1cdbc11f06d4966698f54e1af",
        "sha256_in_prefix": "444e13f8d25bc0e1b513720f65e17216f6e20da1cdbc11f06d4966698f54e1af",
        "size_in_bytes": 4934
      },
      {
        "_path": "Library/include/H5LDpublic.h",
        "path_type": "hardlink",
        "sha256": "21edfe2f7e11ac882a4cb0730b1a2cadde01ba9e99d229a8faa8517a89132145",
        "sha256_in_prefix": "21edfe2f7e11ac882a4cb0730b1a2cadde01ba9e99d229a8faa8517a89132145",
        "size_in_bytes": 1362
      },
      {
        "_path": "Library/include/H5LTpublic.h",
        "path_type": "hardlink",
        "sha256": "62dc195763c4e38e3d27528176dfad53e619ae8aa422825a763cfeee75a9d0e0",
        "sha256_in_prefix": "62dc195763c4e38e3d27528176dfad53e619ae8aa422825a763cfeee75a9d0e0",
        "size_in_bytes": 14182
      },
      {
        "_path": "Library/include/H5LaccProp.h",
        "path_type": "hardlink",
        "sha256": "53fe569da2a18e9ab577b5ae57dde1d9fcbdec3180a36b2889203683d885813e",
        "sha256_in_prefix": "53fe569da2a18e9ab577b5ae57dde1d9fcbdec3180a36b2889203683d885813e",
        "size_in_bytes": 2704
      },
      {
        "_path": "Library/include/H5LcreatProp.h",
        "path_type": "hardlink",
        "sha256": "2ca8727ca950d1493096cc9bc1c2882be1b141f6899ce08071198bef2580e348",
        "sha256_in_prefix": "2ca8727ca950d1493096cc9bc1c2882be1b141f6899ce08071198bef2580e348",
        "size_in_bytes": 2682
      },
      {
        "_path": "Library/include/H5Library.h",
        "path_type": "hardlink",
        "sha256": "02e0aab06e76859d412233c4824dab24281359960606bca5b5452de6f4ce7b2b",
        "sha256_in_prefix": "02e0aab06e76859d412233c4824dab24281359960606bca5b5452de6f4ce7b2b",
        "size_in_bytes": 2881
      },
      {
        "_path": "Library/include/H5Location.h",
        "path_type": "hardlink",
        "sha256": "c9027aafe4df4cc76442118490575344d16e9e0593a20d2c361b0dc18222bf3e",
        "sha256_in_prefix": "c9027aafe4df4cc76442118490575344d16e9e0593a20d2c361b0dc18222bf3e",
        "size_in_bytes": 18199
      },
      {
        "_path": "Library/include/H5Lpublic.h",
        "path_type": "hardlink",
        "sha256": "7da0c270e41f9cea5093caca409218f66b0867c593459708a940486d5dbe88fe",
        "sha256_in_prefix": "7da0c270e41f9cea5093caca409218f66b0867c593459708a940486d5dbe88fe",
        "size_in_bytes": 10160
      },
      {
        "_path": "Library/include/H5MMpublic.h",
        "path_type": "hardlink",
        "sha256": "58eea759085534eea34abc2197d721c19ff5f8dd5bdac39ca2e784093af77ba8",
        "sha256_in_prefix": "58eea759085534eea34abc2197d721c19ff5f8dd5bdac39ca2e784093af77ba8",
        "size_in_bytes": 1775
      },
      {
        "_path": "Library/include/H5Object.h",
        "path_type": "hardlink",
        "sha256": "6b6f1487ec3ef441f61b5ddc5fe42e7ebc32fed10cfc0a8aa923acb1febc5670",
        "sha256_in_prefix": "6b6f1487ec3ef441f61b5ddc5fe42e7ebc32fed10cfc0a8aa923acb1febc5670",
        "size_in_bytes": 5845
      },
      {
        "_path": "Library/include/H5OcreatProp.h",
        "path_type": "hardlink",
        "sha256": "f0ccbdc2f1fd8bcc96feb3a455b6a8db09815be3f54616d73f3342f95d7a1786",
        "sha256_in_prefix": "f0ccbdc2f1fd8bcc96feb3a455b6a8db09815be3f54616d73f3342f95d7a1786",
        "size_in_bytes": 3004
      },
      {
        "_path": "Library/include/H5Opublic.h",
        "path_type": "hardlink",
        "sha256": "0d895a0908139c987addd0f2a0a6463341c60cba613ac34a49ddc02e6ff7aeae",
        "sha256_in_prefix": "0d895a0908139c987addd0f2a0a6463341c60cba613ac34a49ddc02e6ff7aeae",
        "size_in_bytes": 12833
      },
      {
        "_path": "Library/include/H5PLextern.h",
        "path_type": "hardlink",
        "sha256": "300ea50bbddbc12b7acac5347434d986f8accfb58964ef09dff0fe6d0773c963",
        "sha256_in_prefix": "300ea50bbddbc12b7acac5347434d986f8accfb58964ef09dff0fe6d0773c963",
        "size_in_bytes": 1528
      },
      {
        "_path": "Library/include/H5PLpublic.h",
        "path_type": "hardlink",
        "sha256": "74cd924a318e9ef36cdb7d13257ff2baa9c85f38a18000b6d2cf7ad344d3d8b5",
        "sha256_in_prefix": "74cd924a318e9ef36cdb7d13257ff2baa9c85f38a18000b6d2cf7ad344d3d8b5",
        "size_in_bytes": 2402
      },
      {
        "_path": "Library/include/H5PTpublic.h",
        "path_type": "hardlink",
        "sha256": "d673c5f660ce69931fda2dbfda1fc633207ef606192a4aca0d5c99a1616584e3",
        "sha256_in_prefix": "d673c5f660ce69931fda2dbfda1fc633207ef606192a4aca0d5c99a1616584e3",
        "size_in_bytes": 3861
      },
      {
        "_path": "Library/include/H5PacketTable.h",
        "path_type": "hardlink",
        "sha256": "f5649e94dcb3ee6675654f9e021f35a107e1c833b8c728c05833f2bd95869830",
        "sha256_in_prefix": "f5649e94dcb3ee6675654f9e021f35a107e1c833b8c728c05833f2bd95869830",
        "size_in_bytes": 7720
      },
      {
        "_path": "Library/include/H5Ppublic.h",
        "path_type": "hardlink",
        "sha256": "2e8acd6a4fcdeb34a48a4428821254c14365a2a7e62e6210f25996ea7f5d8adc",
        "sha256_in_prefix": "2e8acd6a4fcdeb34a48a4428821254c14365a2a7e62e6210f25996ea7f5d8adc",
        "size_in_bytes": 29027
      },
      {
        "_path": "Library/include/H5PredType.h",
        "path_type": "hardlink",
        "sha256": "e97b87108154974ddf69af33b8a96efb2cd953b6ac7b27f7e4a906910cb8e866",
        "sha256_in_prefix": "e97b87108154974ddf69af33b8a96efb2cd953b6ac7b27f7e4a906910cb8e866",
        "size_in_bytes": 16005
      },
      {
        "_path": "Library/include/H5PropList.h",
        "path_type": "hardlink",
        "sha256": "31e08b0036a9cad6a4718b79492f8af62b4d9c2722d72803577c5590937a27ec",
        "sha256_in_prefix": "31e08b0036a9cad6a4718b79492f8af62b4d9c2722d72803577c5590937a27ec",
        "size_in_bytes": 5850
      },
      {
        "_path": "Library/include/H5Rpublic.h",
        "path_type": "hardlink",
        "sha256": "9e94a1082d9466a4799a0a9377dead54eab95dee67325dc94a631e30cae86ca9",
        "sha256_in_prefix": "9e94a1082d9466a4799a0a9377dead54eab95dee67325dc94a631e30cae86ca9",
        "size_in_bytes": 3794
      },
      {
        "_path": "Library/include/H5Spublic.h",
        "path_type": "hardlink",
        "sha256": "720c3b07ea524ec92b337ae26a4f0286d8577563b6d071bba2f3d99686719e19",
        "sha256_in_prefix": "720c3b07ea524ec92b337ae26a4f0286d8577563b6d071bba2f3d99686719e19",
        "size_in_bytes": 7526
      },
      {
        "_path": "Library/include/H5StrType.h",
        "path_type": "hardlink",
        "sha256": "99d72306fd3d74ec32524c6d7e5772af6e380720377e14e7f4e555fcf543408f",
        "sha256_in_prefix": "99d72306fd3d74ec32524c6d7e5772af6e380720377e14e7f4e555fcf543408f",
        "size_in_bytes": 3040
      },
      {
        "_path": "Library/include/H5TBpublic.h",
        "path_type": "hardlink",
        "sha256": "ac60ec4e99f18d9e37768dd419fff0a22ee7bb65400c7150b75e8beeebff393c",
        "sha256_in_prefix": "ac60ec4e99f18d9e37768dd419fff0a22ee7bb65400c7150b75e8beeebff393c",
        "size_in_bytes": 8419
      },
      {
        "_path": "Library/include/H5Tpublic.h",
        "path_type": "hardlink",
        "sha256": "700e324d9c641b1fbe7f71378be8fa61231405b3301add2f0fb4539cd918f13c",
        "sha256_in_prefix": "700e324d9c641b1fbe7f71378be8fa61231405b3301add2f0fb4539cd918f13c",
        "size_in_bytes": 27251
      },
      {
        "_path": "Library/include/H5VarLenType.h",
        "path_type": "hardlink",
        "sha256": "dcd34504cdb2331d911eb8e46bad327fd05d21ec8d7925642c0292d0af8a56e0",
        "sha256_in_prefix": "dcd34504cdb2331d911eb8e46bad327fd05d21ec8d7925642c0292d0af8a56e0",
        "size_in_bytes": 2468
      },
      {
        "_path": "Library/include/H5Zpublic.h",
        "path_type": "hardlink",
        "sha256": "62004b5128f6105dd716b7a9ef59d5c77daa89e8cf04c0d3972bece2b289865a",
        "sha256_in_prefix": "62004b5128f6105dd716b7a9ef59d5c77daa89e8cf04c0d3972bece2b289865a",
        "size_in_bytes": 11250
      },
      {
        "_path": "Library/include/H5api_adpt.h",
        "path_type": "hardlink",
        "sha256": "9da5d84f391184e2361418cd3b7b2b7bf615e5b9c950a6b24c4fdfa408fbd928",
        "sha256_in_prefix": "9da5d84f391184e2361418cd3b7b2b7bf615e5b9c950a6b24c4fdfa408fbd928",
        "size_in_bytes": 9720
      },
      {
        "_path": "Library/include/H5overflow.h",
        "path_type": "hardlink",
        "sha256": "fbdacf9a50900aa2d6933861b2f114a11ebe529a4a9cb57b8d27bd8dadf1be43",
        "sha256_in_prefix": "fbdacf9a50900aa2d6933861b2f114a11ebe529a4a9cb57b8d27bd8dadf1be43",
        "size_in_bytes": 116154
      },
      {
        "_path": "Library/include/H5pubconf.h",
        "path_type": "hardlink",
        "sha256": "84e4006f4893b300588112ce212688fb877a02771415078a91dc40ef53030161",
        "sha256_in_prefix": "84e4006f4893b300588112ce212688fb877a02771415078a91dc40ef53030161",
        "size_in_bytes": 22584
      },
      {
        "_path": "Library/include/H5public.h",
        "path_type": "hardlink",
        "sha256": "5d5ae6151fb0632b9c8b597bf346bb11c31f345c3397e7e8b1b4d2a8f96e8f3c",
        "sha256_in_prefix": "5d5ae6151fb0632b9c8b597bf346bb11c31f345c3397e7e8b1b4d2a8f96e8f3c",
        "size_in_bytes": 12245
      },
      {
        "_path": "Library/include/H5version.h",
        "path_type": "hardlink",
        "sha256": "ac7d0de0766c4dc5c2cf99044c36898098a17475868337bd92ce4a8a037ff69f",
        "sha256_in_prefix": "ac7d0de0766c4dc5c2cf99044c36898098a17475868337bd92ce4a8a037ff69f",
        "size_in_bytes": 19381
      },
      {
        "_path": "Library/include/hdf5.h",
        "path_type": "hardlink",
        "sha256": "7884dd1efef8fce1dc6ec67568304fe562afba2f2c2592741b344e3374e65bf6",
        "sha256_in_prefix": "7884dd1efef8fce1dc6ec67568304fe562afba2f2c2592741b344e3374e65bf6",
        "size_in_bytes": 3341
      },
      {
        "_path": "Library/include/hdf5_hl.h",
        "path_type": "hardlink",
        "sha256": "c26d1ae182d7a1bbd8681418d18412925eecd03085fb8dc5beea8ff86e217484",
        "sha256_in_prefix": "c26d1ae182d7a1bbd8681418d18412925eecd03085fb8dc5beea8ff86e217484",
        "size_in_bytes": 1543
      },
      {
        "_path": "Library/lib/hdf5.lib",
        "path_type": "hardlink",
        "sha256": "739bd81628c90317e4ca5cc2e98c7a1a4847fa598f012d3075359ca4495a050d",
        "sha256_in_prefix": "739bd81628c90317e4ca5cc2e98c7a1a4847fa598f012d3075359ca4495a050d",
        "size_in_bytes": 620698
      },
      {
        "_path": "Library/lib/hdf5_cpp.lib",
        "path_type": "hardlink",
        "sha256": "248f44091f2528213aac90d903e69414d303acf4b223af237b53a72fa4766500",
        "sha256_in_prefix": "248f44091f2528213aac90d903e69414d303acf4b223af237b53a72fa4766500",
        "size_in_bytes": 397230
      },
      {
        "_path": "Library/lib/hdf5_hl.lib",
        "path_type": "hardlink",
        "sha256": "c0784012097b464f1dfbbd8375db1236849ca04f05ae1b343d46954fafb5c44c",
        "sha256_in_prefix": "c0784012097b464f1dfbbd8375db1236849ca04f05ae1b343d46954fafb5c44c",
        "size_in_bytes": 27664
      },
      {
        "_path": "Library/lib/hdf5_hl_cpp.lib",
        "path_type": "hardlink",
        "sha256": "5baf8c17de87581f8953943133d2f207d32a7168efcb6d7bd084ee0ff11c678d",
        "sha256_in_prefix": "5baf8c17de87581f8953943133d2f207d32a7168efcb6d7bd084ee0ff11c678d",
        "size_in_bytes": 11804
      },
      {
        "_path": "Library/lib/hdf5_tools.lib",
        "path_type": "hardlink",
        "sha256": "7eb3a3b4cc8727023f12a987e20421ae762c83cff917f92ca9c3b1e5b0ea3d8f",
        "sha256_in_prefix": "7eb3a3b4cc8727023f12a987e20421ae762c83cff917f92ca9c3b1e5b0ea3d8f",
        "size_in_bytes": 30464
      },
      {
        "_path": "Library/lib/libhdf5.lib",
        "path_type": "hardlink",
        "sha256": "92edc2ccef714d183770152ee4b84bd16b196641fa801efbcb96aa087a942af8",
        "sha256_in_prefix": "92edc2ccef714d183770152ee4b84bd16b196641fa801efbcb96aa087a942af8",
        "size_in_bytes": 10983870
      },
      {
        "_path": "Library/lib/libhdf5.settings",
        "file_mode": "text",
        "path_type": "hardlink",
        "prefix_placeholder": "D:/bld/hdf5_split_1610146385506/_h_env",
        "sha256": "0d41e41cbaf3198ca530a304d4d4d04ae391c525d07eb33acf743b79d46ae757",
        "sha256_in_prefix": "16a3a1536a6adef87f11b7bd11a64b9efe05f1048b9edd60c74c33e450ab2c79",
        "size_in_bytes": 3145
      },
      {
        "_path": "Library/lib/libhdf5_cpp.lib",
        "path_type": "hardlink",
        "sha256": "eb8727dbd52ee7d6d17df2b53ac735cb98bba53923654293fb98161864facebc",
        "sha256_in_prefix": "eb8727dbd52ee7d6d17df2b53ac735cb98bba53923654293fb98161864facebc",
        "size_in_bytes": 3075072
      },
      {
        "_path": "Library/lib/libhdf5_hl.lib",
        "path_type": "hardlink",
        "sha256": "825411fa601db066c9e4cb8624f76c0d5941e3e00ecf86b5f19f6457c06ca06b",
        "sha256_in_prefix": "825411fa601db066c9e4cb8624f76c0d5941e3e00ecf86b5f19f6457c06ca06b",
        "size_in_bytes": 304706
      },
      {
        "_path": "Library/lib/libhdf5_hl_cpp.lib",
        "path_type": "hardlink",
        "sha256": "08033702e06a23b33645260a3b37d67512cb362b2b07511e0b9ef26e450d1558",
        "sha256_in_prefix": "08033702e06a23b33645260a3b37d67512cb362b2b07511e0b9ef26e450d1558",
        "size_in_bytes": 16984
      },
      {
        "_path": "Library/lib/libhdf5_tools.lib",
        "path_type": "hardlink",
        "sha256": "edbe34e5ad3de2372db398c2b790d4a4f9d1ee34341cd45cefd9d3d17bfc184d",
        "sha256_in_prefix": "edbe34e5ad3de2372db398c2b790d4a4f9d1ee34341cd45cefd9d3d17bfc184d",
        "size_in_bytes": 610338
      },
      {
        "_path": "Library/lib/pkgconfig/hdf5-1.10.5.pc",
        "file_mode": "text",
        "path_type": "hardlink",
        "prefix_placeholder": "D:/bld/hdf5_split_1610146385506/_h_env",
        "sha256": "048cf4bdbcd9d149da1a2a2177ebc9f45a01b16879f6b550b72dc7a72ac7838a",
        "sha256_in_prefix": "ba66f48290651c99aa8653e3db62784e12627d8a999d8e0e53000982f2de959c",
        "size_in_bytes": 400
      },
      {
        "_path": "Library/lib/pkgconfig/hdf5_cpp-1.10.5.pc",
        "file_mode": "text",
        "path_type": "hardlink",
        "prefix_placeholder": "D:/bld/hdf5_split_1610146385506/_h_env",
        "sha256": "ece3007b6f96809ac49c22af30ede9f474927c78d300bd32c898d26b48026f5f",
        "sha256_in_prefix": "ae7d4189ee4b0a23809627201e47be2860ea57081d9729f50bea818184892091",
        "size_in_bytes": 361
      },
      {
        "_path": "Library/lib/pkgconfig/hdf5_hl-1.10.5.pc",
        "file_mode": "text",
        "path_type": "hardlink",
        "prefix_placeholder": "D:/bld/hdf5_split_1610146385506/_h_env",
        "sha256": "1fe5a9ba0ca3da476621791892a9ad6dd05f024554bfd66a99de8c6469df703a",
        "sha256_in_prefix": "258d73cb68406a48e04f985a2b7b2998d3eebec3f4c61c2fe42eef6de780b789",
        "size_in_bytes": 358
      },
      {
        "_path": "Library/lib/pkgconfig/hdf5_hl_cpp-1.10.5.pc",
        "file_mode": "text",
        "path_type": "hardlink",
        "prefix_placeholder": "D:/bld/hdf5_split_1610146385506/_h_env",
        "sha256": "ec52ab1352c67c987b322d9e9b8c7f60d625920cc320ada8f85baa35f902ed51",
        "sha256_in_prefix": "975f008bbbe965c76da63eb227eecb3686fe332c9b5e989ac26c2ded98a190ce",
        "size_in_bytes": 376
      }
    ],
    "paths_version": 1
  },
  "requested_spec": "None",
  "sha256": "ae6f6a7ebde001513f3c42175281c260552da2f67b54cd0a0e3b187f61469917",
  "size": 20202357,
  "subdir": "win-64",
  "timestamp": 1610147555056,
  "track_features": "",
  "url": "https://conda.anaconda.org/conda-forge/win-64/hdf5-1.10.5-nompi_h4d922ce_1114.tar.bz2",
  "version": "1.10.5"
}