<?xml version="1.0" encoding="UTF-8"?>
<metadata xml:lang="en"><Esri><CreaDate>20210624</CreaDate><CreaTime>17021600</CreaTime><ArcGISFormat>1.0</ArcGISFormat><SyncOnce>TRUE</SyncOnce><DataProperties><lineage><Process ToolSource="c:\program files\arcgis\pro\Resources\ArcToolbox\toolboxes\Spatial Analyst Tools.tbx\Curvature" Date="20210624" Time="170216">Curvature dem_lidar_10m.tif "C:\Users\Lewis\Curtin\GDVII - General\Work Package 1\Dempster\royhill\nicher\lidar\dem_lidar_10m_curvature.tif" 1 # #</Process></lineage></DataProperties></Esri></metadata>
